[
    {
        "id": "1",
        "title": "Фестиваль еды",
        "description": "Лучшие уличные кухни города!",
        "date": "2025-05-20T15:00:00Z",
        "location": {
            "lat": 56.847105, 
            "lng": 53.198904
        },
        "isFavorite": false,
        "image": "/eventImg/1.png"
    },
    {
        "id": "2",
        "title": "Концерт в парке",
        "description": "Живая музыка под открытым небом с участием местных рок-групп",
        "date": "2025-05-21T18:00:00Z",
        "location": {
        "lat": 56.859992, 
        "lng": 53.165880
        },
        "isFavorite": false,
        "image": "/eventImg/2.png"
    },
    {
        "id": "3",
        "title": "Опера 'Евгений Онегин' в Государственном театре",
        "description": "Классическая постановка с живым оркестром в честь 200-летия Чайковского",
        "date": "2025-06-15T19:00:00Z",
        "location": {
        "lat": 56.852059,
        "lng": 53.209338
        },
        "isFavorite": false,
        "image": "/eventImg/3.png"
    },
    {
        "id": "4",
        "title": "Выставка оружия в Музее Калашникова",
        "description": "Специальная экспозиция редких моделей и мастер-класс по сборке АК-47",
        "date": "2025-07-10T10:00:00Z",
        "location": {
        "lat": 56.850618,
        "lng": 53.206951
        },
        "isFavorite": false,
        "image": "/eventImg/4.png"
    },
    {
        "id": "5",
        "title": "Этнографическая выставка в Национальном музее",
        "description": "Экспозиция традиций удмуртов с живыми демонстрациями ремесел",
        "date": "2025-08-20T14:00:00Z",
        "location": {
        "lat": 56.853461,
        "lng": 53.215552
        },
        "isFavorite": false,
        "image": "/eventImg/5.png"
    },
    {
        "id": "6",
        "title": "Сеанс в кинотеатре 'Империя грёз'",
        "description": "Премьера фантастического фильма с 3D-эффектами",
        "date": "2025-09-05T16:30:00Z",
        "location": {
        "lat": 56.857189,
        "lng": 53.211002
        },
        "isFavorite": false,
        "image": "/eventImg/6.png"
    },
    {
        "id": "7",
        "title": "День открытых дверей в Ижевском зоопарке",
        "description": "Бесплатный вход и встреча с новыми детенышами тигров",
        "date": "2025-10-12T11:00:00Z",
        "location": {
        "lat": 56.865227,
        "lng": 53.173913
        },
        "isFavorite": false,
        "image": "/eventImg/7.png"
    },
    {
        "id": "8",
        "title": "Сеанс в кинотеатре 'Киномакс'",
        "description": "Романтическая комедия с участием российских актеров",
        "date": "2025-11-18T19:00:00Z",
        "location": {
        "lat": 56.876394,
        "lng": 53.204168
        },
        "isFavorite": false,
        "image": "/eventImg/8.png"
    },
    {
        "id": "9",
        "title": "Исторический лекторий в Центре истории спорта",
        "description": "Лекция о развитии спорта в Удмуртии с показом архивных видео",
        "date": "2025-12-01T15:00:00Z",
        "location": {
        "lat": 56.880715,
        "lng": 53.223096
        },
        "isFavorite": false,
        "image": "/eventImg/9.png"
    },
    {
        "id": "10",
        "title": "Научная конференция в Удмуртском госуниверситете",
        "description": "Международный форум по экологии и устойчивому развитию",
        "date": "2025-06-25T09:00:00Z",
        "location": {
        "lat": 56.850516,
        "lng": 53.223806
        },
        "isFavorite": false,
        "image": "/eventImg/10.png"
    },
    {
        "id": "11",
        "title": "Технический фестиваль в ИжГТУ",
        "description": "Выставка роботов и конкурс инженерных проектов",
        "date": "2025-09-20T13:00:00Z",
        "location": {
        "lat": 56.870976,
        "lng": 53.174417
        },
        "isFavorite": false,
        "image": "/eventImg/11.png"
    },
    {
        "id": "12",
        "title": "Аграрный форум в Удмуртском аграрном университете",
        "description": "Демонстрация инноваций в сельском хозяйстве",
        "date": "2025-07-30T10:00:00Z",
        "location": {
        "lat": 56.873097,
        "lng": 53.172655
        },
        "isFavorite": false,
        "image": "/eventImg/12.png"
    },
    {
        "id": "13",
        "title": "Футбольный матч на стадионе 'Зенит'",
        "description": "Матч чемпионата Удмуртии с участием местных команд",
        "date": "2025-08-15T17:00:00Z",
        "location": {
        "lat": 56.849044,
        "lng": 53.230319
        },
        "isFavorite": false,
        "image": "/eventImg/13.png"
    },
    {
        "id": "14",
        "title": "Баскетбольный турнир в 'Динамо'",
        "description": "Турнир среди молодежных команд с призами",
        "date": "2025-10-05T15:00:00Z",
        "location": {
        "lat": 56.847671,
        "lng": 53.211140
        },
        "isFavorite": false,
        "image": "/eventImg/14.png"
    },
    {
        "id": "15",
        "title": "Цирковое шоу в Государственном цирке",
        "description": "Новая программа с акробатами и дрессированными животными",
        "date": "2025-11-30T18:00:00Z",
        "location": {
        "lat": 56.841448,
        "lng": 53.210388
        },
        "isFavorite": false,
        "image": "/eventImg/15.png"
    }
]
